mk/__init__.py
mk/__main__.py
mk/bin/um.exe
music_tool_kit-1.3.36.dist-info/LICENSE
music_tool_kit-1.3.36.dist-info/METADATA
music_tool_kit-1.3.36.dist-info/WHEEL
music_tool_kit-1.3.36.dist-info/entry_points.txt
music_tool_kit-1.3.36.dist-info/top_level.txt
music_tool_kit-1.3.36.dist-info/RECORD
