Metadata-Version: 2.1
Name: music-tool-kit
Version: 1.3.36
Summary: A tool kit for music download and clip
Home-page: https://github.com/nichuanfang/music-tool-kit
Author: Nichuan Fang
Author-email: f18326186224@gmail.com
License: MIT
Project-URL: Source Code, https://github.com/nichuanfang/music-tool-kit
Project-URL: Bug Tracker, https://github.com/nichuanfang/music-tool-kit/issues
Project-URL: Documentation, https://blog.jaychou.site/2023/12/02/music-tool-kit%E5%B7%A5%E5%85%B7/
Keywords: mkmtkmusic,musictool,musicdownload,musicclip,musickit,musictoolkit
Platform: any
Classifier: Development Status :: 1 - Planning
Classifier: Environment :: Console
Classifier: Intended Audience :: Developers
Classifier: Natural Language :: Chinese (Simplified)
Classifier: Operating System :: OS Independent
Classifier: Programming Language :: Python :: 3.11
Classifier: Topic :: Multimedia :: Sound/Audio
Classifier: Topic :: Utilities
Requires-Python: >=3.11
License-File: LICENSE
Requires-Dist: bilibili-api-python==16.3.0
Requires-Dist: rich==13.7.1
Requires-Dist: setuptools==70.0.0
Requires-Dist: yt-dlp==2024.9.27
